cadenza/__init__.py
legato/__init__.py
fenda-0.0.1.dist-info/METADATA
fenda-0.0.1.dist-info/WHEEL
fenda-0.0.1.dist-info/top_level.txt
fenda-0.0.1.dist-info/RECORD
